MANIFEST.in
setup.cfg
setup.py
django_smart_selects_inlines.egg-info/PKG-INFO
django_smart_selects_inlines.egg-info/SOURCES.txt
django_smart_selects_inlines.egg-info/dependency_links.txt
django_smart_selects_inlines.egg-info/top_level.txt
smart_selects/__init__.py
smart_selects/db_fields.py
smart_selects/form_fields.py
smart_selects/models.py
smart_selects/tests.py
smart_selects/urls.py
smart_selects/utils.py
smart_selects/views.py
smart_selects/widgets.py
smart_selects/static/smart-selects/admin/js/chainedfk.js
smart_selects/static/smart-selects/admin/js/chainedm2m.js
test_app/__init__.py
test_app/admin.py
test_app/models.py
test_app/settings.py
test_app/tests.py
test_app/urls.py
test_app/fixtures/chained_m2m_select.json
test_app/fixtures/chained_select.json
test_app/fixtures/grouped_select.json
test_app/fixtures/user.json
test_app/migrations/0001_initial.py
test_app/migrations/0002_book1_location1.py
test_app/migrations/0003_auto_20160129_1531.py
test_app/migrations/__init__.py